boba/__init__.py
boba/adg.py
boba/baseparser.py
boba/blocksyntaxparser.py
boba/bobarun.py
boba/cli.py
boba/codeparser.py
boba/conditionparser.py
boba/constraintparser.py
boba/decisionparser.py
boba/graphanalyzer.py
boba/graphparser.py
boba/lang.py
boba/parser.py
boba/util.py
boba/wrangler.py
boba/output/__init__.py
boba/output/csvmerger.py
boba-1.1.2.dist-info/LICENSE
boba-1.1.2.dist-info/METADATA
boba-1.1.2.dist-info/WHEEL
boba-1.1.2.dist-info/entry_points.txt
boba-1.1.2.dist-info/top_level.txt
boba-1.1.2.dist-info/RECORD
