Metadata-Version: 2.1
Name: boba
Version: 1.1.2
Summary: Author and execute multiverse analysis
Home-page: https://github.com/uwdata/boba
Author: Yang Liu
Author-email: yliu0@uw.edu
License: BSD license
Keywords: multiverse analysis
Platform: UNKNOWN
Classifier: Development Status :: 3 - Alpha
Classifier: Intended Audience :: Science/Research
Classifier: License :: OSI Approved :: BSD License
Classifier: Natural Language :: English
Classifier: Programming Language :: Python :: 3
Classifier: Programming Language :: Python :: 3.6
Classifier: Programming Language :: Python :: 3.7
Requires-Dist: Click (>=6.0)
Requires-Dist: dataclasses (>=0.6)
Requires-Dist: pandas (>=1.0.1)
